tc_utils/__init__.py
tc_utils/cli/commands/__init__.py
tc_utils/config/settings.py
tc_utils/core/__init__.py
tc_utils/core/command.py
tc_utils/core/registry.py
tc_utils/tools/__init__.py
tc_utils/tools/blast/__init__.py
tc_utils/tools/blast/blast_match_count.py
tc_utils/tools/rnaseq/__init__.py
tc_utils/tools/rnaseq/ma_plot.py
tc_utils/tools/vcf/__init__.py
tc_utils/tools/vcf/genome_similarity.py
tcuni_bio_utils-0.1.1.dist-info/METADATA
tcuni_bio_utils-0.1.1.dist-info/WHEEL
tcuni_bio_utils-0.1.1.dist-info/entry_points.txt
tcuni_bio_utils-0.1.1.dist-info/RECORD
