Metadata-Version: 2.4
Name: tcuni-bio-utils
Version: 0.1.1
Summary: scripts collection for tcuni bio data process
Project-URL: Repository, https://github.com/username/tc-utils
Author-email: brightrock <ricekent@163.com>
License: MIT
Requires-Python: >=3.12
Requires-Dist: matplotlib>=3.6.3
Requires-Dist: pandas>=2.2.2
Requires-Dist: pydantic>=2
Requires-Dist: pysam>=0.23.0
Requires-Dist: tqdm>=4
Requires-Dist: typer>=0.15.0
